pygum/__init__.py
pygum/_command_wrapper.py
pygum/_gum.py
pygum-0.1.0.dist-info/LICENSE
pygum-0.1.0.dist-info/WHEEL
pygum-0.1.0.dist-info/METADATA
pygum-0.1.0.dist-info/RECORD
